setu_mcp_upi_deeplinks/__init__.py
setu_mcp_upi_deeplinks/server.py
setu_mcp_upi_deeplinks-0.1.0.dist-info/METADATA
setu_mcp_upi_deeplinks-0.1.0.dist-info/WHEEL
setu_mcp_upi_deeplinks-0.1.0.dist-info/entry_points.txt
setu_mcp_upi_deeplinks-0.1.0.dist-info/RECORD
