Metadata-Version: 2.4
Name: setu_mcp_upi_deeplinks
Version: 0.1.0
Summary: A MCP server for Setu UPI Deeplinks APIs providing payment link generation and management
Project-URL: Homepage, https://setu.co
Project-URL: Repository, https://github.com/SetuHQ/setu-mcps/tree/main/upi-deeplinks
Project-URL: Documentation, https://github.com/SetuHQ/setu-mcps/tree/main/upi-deeplinks
Author-email: Kaustav Banerjee <kaustav@setu.co>
License-Expression: MIT
Keywords: deeplinks,mcp,payments,setu,setu_mcp_upi_deeplinks,upi
Classifier: Development Status :: 4 - Beta
Classifier: Intended Audience :: Developers
Classifier: License :: OSI Approved :: MIT License
Classifier: Programming Language :: Python :: 3
Classifier: Programming Language :: Python :: 3.12
Classifier: Topic :: Software Development :: Libraries :: Python Modules
Requires-Python: >=3.12
Requires-Dist: mcp>=1.2.0
Requires-Dist: pydantic>=2.0.0
Requires-Dist: python-dotenv>=1.0.0
Requires-Dist: setu>=2.1.0
